{
  "type": "enchantment_infusion:enchantment_infusion",
  "enchantment": "minecraft:piercing",
  "force": false,
  "ingredients": [
    {
      "item": "minecraft:clock"
    },
    {
      "item": "minecraft:clock"
    },
    {
      "item": "minecraft:clock"
    },
    {
      "item": "minecraft:amethyst_shard"
    },
    {
      "item": "minecraft:amethyst_shard"
    },
    {
      "item": "minecraft:lapis_block"
    },
    {
      "item": "minecraft:lapis_block"
    }
  ],
  "input": {
    "enchantment": "minecraft:piercing",
    "min_level": 2
  },
  "level": 3
}